misc/__init__.py
misc/cmod5n.py
spectral_analyses/__init__.py
spectral_analyses/equations_sar.py
spectral_analyses/sar_analysis.py
sentinel_analyses-0.0.0.dist-info/LICENSE
sentinel_analyses-0.0.0.dist-info/METADATA
sentinel_analyses-0.0.0.dist-info/WHEEL
sentinel_analyses-0.0.0.dist-info/top_level.txt
sentinel_analyses-0.0.0.dist-info/RECORD
